pypad2/__init__.py
pypad2/gamepad.py
pypad2/keymaps.py
pypad2-1.0.0.dist-info/LICENSE
pypad2-1.0.0.dist-info/METADATA
pypad2-1.0.0.dist-info/WHEEL
pypad2-1.0.0.dist-info/top_level.txt
pypad2-1.0.0.dist-info/RECORD
