Metadata-Version: 2.1
Name: pypad2
Version: 1.0.0
Summary: Python Gamepad
Home-page: https://github.com/Vinz1911/PyPad2
Author: Vinzenz Weist
Author-email: Vinz1911@gmail.com
License: GPLv3
Platform: UNKNOWN
Requires-Dist: evdev
